wind/__init__.py
wind/wind.py
wind-0.0.0.dev0.dist-info/METADATA
wind-0.0.0.dev0.dist-info/RECORD
wind-0.0.0.dev0.dist-info/WHEEL
wind-0.0.0.dev0.dist-info/top_level.txt
